AutoApiTestRunner/__init__.py
AutoApiTestRunner/auto.py
AutoApiTestRunner/config.py
AutoApiTestRunner-1.0.3.dist-info/LICENSE
AutoApiTestRunner-1.0.3.dist-info/METADATA
AutoApiTestRunner-1.0.3.dist-info/WHEEL
AutoApiTestRunner-1.0.3.dist-info/entry_points.txt
AutoApiTestRunner-1.0.3.dist-info/top_level.txt
AutoApiTestRunner-1.0.3.dist-info/RECORD
