Metadata-Version: 2.1
Name: AutoApiTestRunner
Version: 1.0.3
Summary: A Command Line Interface to run Shuttl API tests
Home-page: https://github.com/kshamashuttl
Author: Kshama Singh
Author-email: kshama.singh@shuttl.com
License: UNKNOWN
Platform: UNKNOWN
Requires-Dist: Click
Requires-Dist: Requests
